measurer/__init__.py
measurer/__main__.py
function_measurer-0.3.2.dist-info/LICENSE
function_measurer-0.3.2.dist-info/METADATA
function_measurer-0.3.2.dist-info/WHEEL
function_measurer-0.3.2.dist-info/top_level.txt
function_measurer-0.3.2.dist-info/RECORD
