Metadata-Version: 2.1
Name: function-measurer
Version: 0.3.2
Summary: Python utility for compairing functions and other callable objects.
Author: InternetStalker
Author-email: internetstalcker@yandex.ru
License: MIT
Project-URL: Homepage, https://github.com/InternetStalker/function_measurer
Keywords: test tests testing runtime memory
Platform: UNKNOWN
Classifier: License :: OSI Approved :: MIT License
Classifier: Operating System :: Microsoft :: Windows
Classifier: Programming Language :: Python :: 3
Classifier: Topic :: Software Development :: Libraries :: Python Modules
Classifier: Topic :: Utilities
License-File: LICENSE
Requires-Dist: simple-file-user
